hlsf_module/__init__.py
hlsf_module/adjacency_expander.py
hlsf_module/adjacency_mapping.py
hlsf_module/agency_gates.py
hlsf_module/cli.py
hlsf_module/clusterer.py
hlsf_module/cross_modal.py
hlsf_module/enc_audio.py
hlsf_module/fft_backends.py
hlsf_module/fft_tokenizer.py
hlsf_module/gating_strategies.py
hlsf_module/geometry.py
hlsf_module/history_viewer.py
hlsf_module/image_encoder.py
hlsf_module/live_visualizer.py
hlsf_module/llm_client.py
hlsf_module/llm_weights.py
hlsf_module/main.py
hlsf_module/modal_stream.py
hlsf_module/multimodal_out.py
hlsf_module/ngram_text_encoder.py
hlsf_module/pipeline_frame.py
hlsf_module/plugins.py
hlsf_module/powerlaw.py
hlsf_module/prototypes.py
hlsf_module/pruning.py
hlsf_module/recursion_ctrl.py
hlsf_module/resonator.py
hlsf_module/rh_config.py
hlsf_module/rh_gate.py
hlsf_module/rh_mapping.py
hlsf_module/rh_utils.py
hlsf_module/rotation_rules.py
hlsf_module/server.py
hlsf_module/signal_io.py
hlsf_module/stream_pipeline.py
hlsf_module/tensor_mapper.py
hlsf_module/text_encoder.py
hlsf_module/text_fft.py
hlsf_module/text_signal.py
hlsf_module/text_stream_pipeline.py
hlsf_module/trainer.py
hlsf_module/verification.py
hlsf_module/visualization.py
hlsf_module/web_api.py
hlsf_module/web_server.py
hlsf_module/web_viewer.py
hlsf_module/weight_cache.py
hlsf_module/weights_bp.py
hlsf_module/data/sample_vocab.json
hlsf_module/data/sample_weights.json
hlsf_module/symbols/__init__.py
hlsf_module/symbols/encoding.py
hlsf_module/symbols/graph.py
hlsf_module/symbols/resonator.py
hlsf_module/symbols/schema.py
hlsf_module/symbols/vocab.py
hlsf_module-0.1.3.dist-info/licenses/LICENSE
src/__init__.py
src/fft_tokenizer.py
hlsf_module-0.1.3.dist-info/METADATA
hlsf_module-0.1.3.dist-info/WHEEL
hlsf_module-0.1.3.dist-info/top_level.txt
hlsf_module-0.1.3.dist-info/RECORD
