Metadata-Version: 2.4
Name: hlsf_module
Version: 0.1.3
Summary: High-Level Space Field toolkit
Author: HLSF Developers
License-Expression: MIT
Keywords: audio,fft,visualization
Classifier: Programming Language :: Python :: 3
Classifier: Operating System :: OS Independent
Requires-Python: >=3.8
License-File: LICENSE
Requires-Dist: numpy>=1.22
Requires-Dist: matplotlib>=3.5
Provides-Extra: audio
Requires-Dist: sounddevice; extra == "audio"
Provides-Extra: fft
Requires-Dist: numpy; extra == "fft"
Requires-Dist: scipy; extra == "fft"
Provides-Extra: gpu
Requires-Dist: cupy; extra == "gpu"
Provides-Extra: visualization
Requires-Dist: matplotlib; extra == "visualization"
Provides-Extra: test
Requires-Dist: pytest; extra == "test"
Requires-Dist: pre-commit; extra == "test"
Provides-Extra: web
Requires-Dist: fastapi; extra == "web"
Requires-Dist: uvicorn; extra == "web"
Requires-Dist: httpx; extra == "web"
Provides-Extra: docs
Requires-Dist: sphinx; extra == "docs"
Requires-Dist: sphinx-autodoc-typehints; extra == "docs"
Dynamic: license-file
